{
  "gsm8k": [
    40,
    49,
    61,
    113,
    121,
    137,
    211,
    215,
    222,
    232,
    235,
    239,
    248
  ],
  "boolq": [
    2,
    12,
    21,
    37,
    42,
    49,
    66,
    88,
    102,
    114,
    119,
    121,
    122,
    124,
    136,
    162,
    174,
    177,
    182,
    188,
    200,
    210,
    224,
    229,
    241,
    249,
    254,
    261,
    262,
    265,
    278,
    283,
    292,
    293
  ],
  "arc-easy": [
    0,
    9,
    27,
    38,
    48,
    54,
    55,
    63,
    66,
    71,
    103,
    104,
    123,
    127,
    151,
    173,
    179,
    184,
    189,
    210,
    214,
    215,
    222,
    232,
    245,
    253,
    255,
    280
  ],
  "commonsenseqa": [
    10,
    33,
    57,
    63,
    75,
    88,
    91,
    118,
    135,
    136,
    140,
    144,
    172,
    174,
    185,
    190,
    199,
    211,
    216,
    230,
    231,
    232,
    241,
    249,
    265,
    269,
    270,
    275,
    299
  ],
  "mmlu-stem": [
    11,
    49,
    61,
    92,
    102,
    126,
    155,
    246,
    250,
    258,
    282
  ]
}